holidays_es/__init__.py
holidays_es/enums.py
holidays_es/exceptions.py
holidays_es/holidays.py
holidays_es/models.py
holidays_es-2.0.0.dist-info/LICENSE
holidays_es-2.0.0.dist-info/METADATA
holidays_es-2.0.0.dist-info/WHEEL
holidays_es-2.0.0.dist-info/RECORD
