Metadata-Version: 2.1
Name: holidays-es
Version: 2.0.0
Summary: Public holidays in Spain from 2006 to now
Home-page: https://github.com/rsolanodev/holidays-es
License: MIT
Author: rsolanodev
Author-email: rubensoljim@gmail.com
Requires-Python: >=3.10,<4.0
Classifier: License :: OSI Approved :: MIT License
Classifier: Operating System :: OS Independent
Classifier: Programming Language :: Python :: 3
Classifier: Programming Language :: Python :: 3.10
Classifier: Programming Language :: Python :: 3.11
Requires-Dist: attrs (>=23.1.0,<24.0.0)
Requires-Dist: beautifulsoup4 (>=4.12.2,<5.0.0)
Requires-Dist: requests (>=2.31.0,<3.0.0)
